agentic_blocks/__init__.py
agentic_blocks/agent.py
agentic_blocks/agent_with_logger.py
agentic_blocks/llm_agno.py
agentic_blocks/llm_structured.py
agentic_blocks/mcp_client.py
agentic_blocks/messages.py
agentic_blocks/models.py
agentic_blocks/streaming/__init__.py
agentic_blocks/streaming/ai_sdk_events.py
agentic_blocks/streaming/main.py
agentic_blocks/streaming/node_context.py
agentic_blocks/streaming/streaming_flow.py
agentic_blocks/streaming/streaming_node_mixin.py
agentic_blocks/utils/config_utils.py
agentic_blocks/utils/logger.py
agentic_blocks/utils/rich_logger.py
agentic_blocks/utils/server_utils.py
agentic_blocks/utils/tools_utils.py
agentic_blocks/visualization/visualize.py
agentic_blocks-0.1.37.dist-info/licenses/LICENSE
agentic_blocks-0.1.37.dist-info/METADATA
agentic_blocks-0.1.37.dist-info/WHEEL
agentic_blocks-0.1.37.dist-info/top_level.txt
agentic_blocks-0.1.37.dist-info/RECORD
