Metadata-Version: 2.4
Name: agentic-blocks
Version: 0.1.37
Summary: Simple building blocks for agentic AI systems with MCP client and conversation management
Author-email: Magnus Bjelkenhed <bjelkenhed@gmail.com>
License: MIT
Project-URL: Homepage, https://github.com/bjelkenhed/agentic-blocks
Project-URL: Repository, https://github.com/bjelkenhed/agentic-blocks
Project-URL: Issues, https://github.com/bjelkenhed/agentic-blocks/issues
Keywords: ai,mcp,model-control-protocol,agent,llm,openai,conversation
Classifier: Development Status :: 3 - Alpha
Classifier: Intended Audience :: Developers
Classifier: License :: OSI Approved :: MIT License
Classifier: Programming Language :: Python :: 3
Classifier: Programming Language :: Python :: 3.11
Classifier: Programming Language :: Python :: 3.12
Classifier: Topic :: Software Development :: Libraries :: Python Modules
Classifier: Topic :: Scientific/Engineering :: Artificial Intelligence
Requires-Python: >=3.11
License-File: LICENSE
Requires-Dist: mcp
Requires-Dist: requests
Requires-Dist: python-dotenv
Requires-Dist: openai
Requires-Dist: langchain-core
Requires-Dist: langfuse
Requires-Dist: pocketflow
Requires-Dist: pocketflow-tracing
Requires-Dist: agno==2.0.9
Requires-Dist: ipywidgets
Requires-Dist: rich[jupyter]
Requires-Dist: fastapi
Requires-Dist: pydantic
Requires-Dist: reactivex
Requires-Dist: fastapi[standard]
Provides-Extra: test
Requires-Dist: pytest; extra == "test"
Provides-Extra: dev
Requires-Dist: pytest; extra == "dev"
Requires-Dist: build; extra == "dev"
Requires-Dist: twine; extra == "dev"
Dynamic: license-file
